pyMIH.py
setup.py
pyMIH.egg-info/PKG-INFO
pyMIH.egg-info/SOURCES.txt
pyMIH.egg-info/dependency_links.txt
pyMIH.egg-info/top_level.txt