Metadata-Version: 1.0
Name: pyMIH
Version: 0.6.1
Summary: Python implementation of Multiple-Index Hashing, an efficient technique for accelerating lookups for fuzzy hashes such as PDQ.
Home-page: https://github.com/AiLECS/pyMIH
Author: Janis Dalins
Author-email: janis.dalins@monash.edu
License: MIT
Platform: UNKNOWN
